notturno/__init__.py
notturno/app.py
notturno/asgi.py
notturno/exceptions.py
notturno/gear.py
notturno/core/http/serv.py
notturno/core/http/models/ssl.py
notturno/core/router/regexp.py
notturno/loops/winloop.py
notturno/models/request.py
notturno/models/response.py
notturno/models/websocket.py
notturno/utils/jsonenc.py
notturno/utils/query.py
notturno/utils/url.py
notturno-0.1.2.dist-info/LICENSE
notturno-0.1.2.dist-info/METADATA
notturno-0.1.2.dist-info/WHEEL
notturno-0.1.2.dist-info/top_level.txt
notturno-0.1.2.dist-info/RECORD
