Metadata-Version: 2.2
Name: notturno
Version: 0.1.2
Summary: ultra-fast HTTP/ASGI Web Framework.
Author-email: AmaseCocoa <cocoa@amase.cc>
License: MIT
Project-URL: Repository, https://github.com/AmaseCocoa/Notturno
Project-URL: Issues, https://github.com/AmaseCocoa/Notturno/issues
Project-URL: Changelog, https://github.com/AmaseCocoa/Notturno/blob/main/CHANGELOG.md
Keywords: asgi,http,http-server,asgi-framework
Classifier: Development Status :: 4 - Beta
Classifier: Intended Audience :: Developers
Classifier: Framework :: AnyIO
Classifier: Framework :: Trio
Classifier: Framework :: AsyncIO
Classifier: Topic :: Software Development :: Libraries
Classifier: Topic :: Software Development :: Libraries :: Application Frameworks
Classifier: License :: OSI Approved :: MIT License
Classifier: Programming Language :: Python :: 3
Classifier: Programming Language :: Python :: 3.10
Classifier: Programming Language :: Python :: 3.11
Classifier: Programming Language :: Python :: 3.12
Classifier: Programming Language :: Python :: 3.13
Requires-Python: >=3.10
License-File: LICENSE
Requires-Dist: pydantic>=2.10.6
Requires-Dist: anyio>=4.8.0
Requires-Dist: yarl>=1.18.3
Requires-Dist: h2>=4.1.0
Requires-Dist: aiomultiprocess>=0.9.1
Requires-Dist: google-re2>=1.1.20240702
Provides-Extra: speed
Requires-Dist: orjson>=3.10.15; extra == "speed"
Requires-Dist: fast-query-parsers>=1.0.3; extra == "speed"
Provides-Extra: trio
Requires-Dist: trio>=0.28.0; extra == "trio"
Provides-Extra: asgi
Requires-Dist: uvicorn>=0.34.0; extra == "asgi"
